xgbsearch/XgbResultDisplay.py
xgbsearch/XgbSearch.py
xgbsearch/XgbSearchExampleData.py
xgbsearch/__init__.py
xgbsearch-0.1.6.dist-info/LICENSE.md
xgbsearch-0.1.6.dist-info/METADATA
xgbsearch-0.1.6.dist-info/WHEEL
xgbsearch-0.1.6.dist-info/top_level.txt
xgbsearch-0.1.6.dist-info/RECORD
