Metadata-Version: 2.1
Name: xgbsearch
Version: 0.1.6
Summary: An implementation of grid search, random search for XGBoost with eval_set and early stopping support.
Author-email: Jakub Deka <jakub.deka@gmail.com>
Maintainer-email: Jakub Deka <jakub.deka@gmail.com>
License: MIT License
Project-URL: Homepage, https://github.com/jakub-deka/xgbsearch
Project-URL: Source, https://github.com/jakub-deka/xgbsearch
Project-URL: Bug Reports, https://github.com/jakub-deka/xgbsearch/issues
Keywords: xgboost
Classifier: Development Status :: 3 - Alpha
Classifier: Operating System :: OS Independent
Classifier: Programming Language :: Python
Classifier: Programming Language :: Python :: 3
Classifier: Programming Language :: Python :: 3.10
Classifier: Programming Language :: Python :: 3.11
Classifier: Programming Language :: Python :: 3.12
Requires-Python: >=3.6
License-File: LICENSE.md
Requires-Dist: numpy
Requires-Dist: pandas
Requires-Dist: xgboost
Requires-Dist: colorama
Requires-Dist: matplotlib
Requires-Dist: seaborn
